Metadata-Version: 2.4
Name: airbyte-agent-mcp
Version: 0.1.102
Summary: MCP server that exposes Airbyte Connector SDK as MCP tools
Author-email: Airbyte Support <support@airbyte.io>
Requires-Python: >=3.13
Requires-Dist: click>=8.0.0
Requires-Dist: fastmcp>=2.10.5
Requires-Dist: httpx>=0.24.0
Requires-Dist: jinja2>=3.0.0
Requires-Dist: jsonpath-ng>=1.6.1
Requires-Dist: jsonref>=1.1.0
Requires-Dist: jsonschema>=4.0.0
Requires-Dist: opentelemetry-api>=1.37.0
Requires-Dist: opentelemetry-sdk>=1.37.0
Requires-Dist: pydantic>=2.0.0
Requires-Dist: python-dotenv>=1.0.0
Requires-Dist: pyyaml>=6.0
Requires-Dist: segment-analytics-python>=2.2.0
Provides-Extra: dev
Requires-Dist: pytest-asyncio<1.0.0,>=0.24.0; extra == 'dev'
Requires-Dist: pytest<9.0.0,>=8.3.3; extra == 'dev'
Requires-Dist: ruff==0.7.3; extra == 'dev'
